{
    "song_number": 690,
    "title": "பாடல் 690",
    "category_or_place": "திருமயிலை",
    "raga": "பூர்வி கல்யாணி",
    "thala": "பொது / குறிப்பிடப்படவில்லை",
    "chandam_structure": "",
    "chandam": [],
    "lyrics": [
        "தகிட-1 1/2, தகதிமி-2",
        "தகதிமி-2, தகதிமிதக-3",
        "தனன தானன தானன தந்தத் ...... தனதான",
        "அறமி லாவதி பாதக வஞ்சத் ...... தொழிலாலே",
        "அடிய னேன்மெலி வாகிம னஞ்சற் ...... றிளையாதே",
        "திறகு லாவிய சேவடி வந்தித் ...... தருள்கூடத்",
        "தினமு மேமிக வாழ்வுறு மின்பைத் ...... தருவாயே",
        "விறல் சாசரர் சேனைக ளஞ்சப் ...... பொரும்வேலா",
        "விமல மாதபி ராமித ருஞ்செய்ப் ...... புதல்வோனே",
        "மறவர் வாணுதல் வேடைகொ ளும்பொற் ...... புயவீரா",
        "மயிலை மாநகர் மேவிய கந்தப் ...... பெருமாளே."
    ],
    "full_text": "தகிட-1 1/2, தகதிமி-2\nதகதிமி-2, தகதிமிதக-3\nதனன தானன தானன தந்தத் ...... தனதான\nஅறமி லாவதி பாதக வஞ்சத் ...... தொழிலாலே\nஅடிய னேன்மெலி வாகிம னஞ்சற் ...... றிளையாதே\nதிறகு லாவிய சேவடி வந்தித் ...... தருள்கூடத்\nதினமு மேமிக வாழ்வுறு மின்பைத் ...... தருவாயே\nவிறல் சாசரர் சேனைக ளஞ்சப் ...... பொரும்வேலா\nவிமல மாதபி ராமித ருஞ்செய்ப் ...... புதல்வோனே\nமறவர் வாணுதல் வேடைகொ ளும்பொற் ...... புயவீரா\nமயிலை மாநகர் மேவிய கந்தப் ...... பெருமாளே."
}