{
    "song_number": 578,
    "title": "பாடல் 578",
    "category_or_place": "விராலிமலை",
    "raga": "...",
    "thala": "பொது / குறிப்பிடப்படவில்லை",
    "chandam_structure": "தானாத்தன தான தனதன / தானாத்தன தான தனதன / தானாத்தன தான தனதன ...... தனதான",
    "chandam": [
        "தானாத்தன தான தனதன",
        "தானாத்தன தான தனதன",
        "தானாத்தன தான தனதன ...... தனதான"
    ],
    "lyrics": [
        "காமாத்திர மாகி யிளைஞர்கள்",
        "வாழ்நாட்கொடு போகி யழகிய",
        "காதாட்டிய பார இருகுழை ...... யளவோடிக்",
        "கார்போற்றவ ழோதி நிழல்தனி",
        "லார்வாட்கடை யீடு கனகொடு",
        "காலேற்றுவை வேலின் முனைகடை ...... யமதூதர்",
        "ஏமாப்பற மோக வியல்செய்து",
        "நீலோற்பல ஆசில் மலருட",
        "னேராட்டவி நோத மிடும்விழி ...... மடவார்பால்",
        "ஏகாப்பழி பூணு மருளற",
        "நீதோற்றிமு னாளு மடிமையை",
        "யீடேற்றுத லாலுன் வலிமையை ...... மறவேனே",
        "சீமாட்டியு மாய திரிபுரை",
        "காலாக்கினி கோப பயிரவி",
        "சீலோத்தமி நீலி சுரதிரி ...... புவநேசை",
        "சீகார்த்திகை யாய அறுவகை",
        "மாதாக்கள்கு மார னெனவெகு",
        "சீராட்டொடு பேண வடதிசை ...... கயிலாசக்",
        "கோமாற்குப தேச முபநிட",
        "வேதார்த்தமெய்ஞ் ஞான நெறியருள்",
        "கோதாட்டி ஸ்வாமி யெனவரு ...... மிளையோனே",
        "கோடாச்சிவ பூஜை பவுருஷ",
        "மாறாக்கொடை நாளு மருவிய",
        "கோனாட்டுவி ராலி மலையுறை ...... பெருமாளே."
    ],
    "full_text": "காமாத்திர மாகி யிளைஞர்கள்\nவாழ்நாட்கொடு போகி யழகிய\nகாதாட்டிய பார இருகுழை ...... யளவோடிக்\nகார்போற்றவ ழோதி நிழல்தனி\nலார்வாட்கடை யீடு கனகொடு\nகாலேற்றுவை வேலின் முனைகடை ...... யமதூதர்\nஏமாப்பற மோக வியல்செய்து\nநீலோற்பல ஆசில் மலருட\nனேராட்டவி நோத மிடும்விழி ...... மடவார்பால்\nஏகாப்பழி பூணு மருளற\nநீதோற்றிமு னாளு மடிமையை\nயீடேற்றுத லாலுன் வலிமையை ...... மறவேனே\nசீமாட்டியு மாய திரிபுரை\nகாலாக்கினி கோப பயிரவி\nசீலோத்தமி நீலி சுரதிரி ...... புவநேசை\nசீகார்த்திகை யாய அறுவகை\nமாதாக்கள்கு மார னெனவெகு\nசீராட்டொடு பேண வடதிசை ...... கயிலாசக்\nகோமாற்குப தேச முபநிட\nவேதார்த்தமெய்ஞ் ஞான நெறியருள்\nகோதாட்டி ஸ்வாமி யெனவரு ...... மிளையோனே\nகோடாச்சிவ பூஜை பவுருஷ\nமாறாக்கொடை நாளு மருவிய\nகோனாட்டுவி ராலி மலையுறை ...... பெருமாளே."
}