{
    "song_number": 776,
    "title": "பாடல் 776",
    "category_or_place": "சீகாழி",
    "raga": "....",
    "thala": "பொது / குறிப்பிடப்படவில்லை",
    "chandam_structure": "தனதனன தத்ததன தனதனன தத்ததன / தனதனன தத்ததன ...... தனதான",
    "chandam": [
        "தனதனன தத்ததன தனதனன தத்ததன",
        "தனதனன தத்ததன ...... தனதான"
    ],
    "lyrics": [
        "விடமெனமி குத்தவட வனலென வுயர்த்துரவி",
        "விரிகதி ரெனப்பரவு ...... நிலவாலே",
        "விதனமிக வுற்றுவரு ரதிபதி கடுத்துவிடு",
        "விரைதரு விதட்கமல ...... கணையாலே",
        "அடலமரி யற்றுதிசை யினில்மருவி மிக்கவனல்",
        "அழலொடு கொதித்துவரு ...... கடைநாளில்",
        "அணுகிநம னெற்றமயல் கொளுமநிலை சித்தமுற",
        "அவசமொ டணைத்தருள ...... வரவேணும்",
        "அடவிதனில் மிக்கபரு வரையவ ரளித்ததிரு",
        "அனையமயில் முத்தமணி ...... சுரயானை",
        "அழகிய மணிக்கலச முலைகளில் மயக்கமுறு",
        "மதிவிரக சித்ரமணி ...... மயில்வீரா",
        "கடதடக ளிற்றுமுக ரிளையவ கிரிக்குமரி",
        "கருணையொ டளித்ததிற ...... முருகோனே",
        "கமலமல ரொத்தவிழி யரிமருக பத்தர்பணி",
        "கழுமலந கர்க்குமர ...... பெருமாளே."
    ],
    "full_text": "விடமெனமி குத்தவட வனலென வுயர்த்துரவி\nவிரிகதி ரெனப்பரவு ...... நிலவாலே\nவிதனமிக வுற்றுவரு ரதிபதி கடுத்துவிடு\nவிரைதரு விதட்கமல ...... கணையாலே\nஅடலமரி யற்றுதிசை யினில்மருவி மிக்கவனல்\nஅழலொடு கொதித்துவரு ...... கடைநாளில்\nஅணுகிநம னெற்றமயல் கொளுமநிலை சித்தமுற\nஅவசமொ டணைத்தருள ...... வரவேணும்\nஅடவிதனில் மிக்கபரு வரையவ ரளித்ததிரு\nஅனையமயில் முத்தமணி ...... சுரயானை\nஅழகிய மணிக்கலச முலைகளில் மயக்கமுறு\nமதிவிரக சித்ரமணி ...... மயில்வீரா\nகடதடக ளிற்றுமுக ரிளையவ கிரிக்குமரி\nகருணையொ டளித்ததிற ...... முருகோனே\nகமலமல ரொத்தவிழி யரிமருக பத்தர்பணி\nகழுமலந கர்க்குமர ...... பெருமாளே."
}