{
    "song_number": 1122,
    "title": "பாடல் 1122",
    "category_or_place": "பொதுப்பாடல்கள்",
    "raga": ".....",
    "thala": "பொது / குறிப்பிடப்படவில்லை",
    "chandam_structure": "தத்தா தத்தா தத்தா தத்தா / தத்தா தத்தத் ...... தனதான",
    "chandam": [
        "தத்தா தத்தா தத்தா தத்தா",
        "தத்தா தத்தத் ...... தனதான"
    ],
    "lyrics": [
        "பொற்பூ வைச்சீ ரைப்போ லப்போ",
        "தப்பே சிப்பொற் ...... கனிவாயின்",
        "பொய்க்கா மத்தே மெய்க்கா மப்பூ",
        "ணைப்பூண் வெற்பிற் ...... றுகில்சாயக்",
        "கற்பா லெக்கா வுட்கோ லிக்கா",
        "சுக்கே கைக்குத் ...... திடுமாதர்",
        "கட்கே பட்டே நெட்டா சைப்பா",
        "டுற்றே கட்டப் ...... படுவேனோ",
        "சொற்கோ லத்தே நற்கா லைச்சே",
        "விப்பார் சித்தத் ...... துறைவோனே",
        "தொக்கே கொக்கா கிச்சூ ழச்சூர்",
        "விக்கா முக்கத் ...... தொடும்வேலா",
        "முற்கா லத்தே வெற்பேய் வுற்றார்",
        "முத்தாள் முத்தச் ...... சிறியோனே",
        "முத்தா முத்தீ யத்தா சுத்தா",
        "முத்தா முத்திப் ...... பெருமாளே."
    ],
    "full_text": "பொற்பூ வைச்சீ ரைப்போ லப்போ\nதப்பே சிப்பொற் ...... கனிவாயின்\nபொய்க்கா மத்தே மெய்க்கா மப்பூ\nணைப்பூண் வெற்பிற் ...... றுகில்சாயக்\nகற்பா லெக்கா வுட்கோ லிக்கா\nசுக்கே கைக்குத் ...... திடுமாதர்\nகட்கே பட்டே நெட்டா சைப்பா\nடுற்றே கட்டப் ...... படுவேனோ\nசொற்கோ லத்தே நற்கா லைச்சே\nவிப்பார் சித்தத் ...... துறைவோனே\nதொக்கே கொக்கா கிச்சூ ழச்சூர்\nவிக்கா முக்கத் ...... தொடும்வேலா\nமுற்கா லத்தே வெற்பேய் வுற்றார்\nமுத்தாள் முத்தச் ...... சிறியோனே\nமுத்தா முத்தீ யத்தா சுத்தா\nமுத்தா முத்திப் ...... பெருமாளே."
}