{
    "song_number": 290,
    "title": "பாடல் 290",
    "category_or_place": "திருத்தணிகை",
    "raga": "....",
    "thala": "பொது / குறிப்பிடப்படவில்லை",
    "chandam_structure": "தனன தத்தன தனன தத்தன / தனன தத்தன ...... தனதான",
    "chandam": [
        "தனன தத்தன தனன தத்தன",
        "தனன தத்தன ...... தனதான"
    ],
    "lyrics": [
        "மலைமு லைச்சியர் கயல்வி ழிச்சியர்",
        "மதிமு கத்திய ...... ரழகான",
        "மயில்ந டைச்சியர் குயில்மொ ழிச்சியர்",
        "மனது ருக்கிக ...... ளணைமீதே",
        "கலைநெ கிழ்த்தியே உறவ ணைத்திடு",
        "கலவி யிற்றுவள் ...... பிணிதீராக்",
        "கசட னைக்குண அசட னைப்புகல்",
        "கதியில் வைப்பது ...... மொருநாளே",
        "குலகி ரிக்குல முருவ விட்டமர்",
        "குலவு சித்திர ...... முனைவேலா",
        "குறவர் பெற்றிடு சிறுமி யைப்புணர்",
        "குமர சற்குண ...... மயில்வீரா",
        "தலம திற்புக லமர ருற்றிடர்",
        "தனைய கற்றிய ...... அருளாளா",
        "தருநி ரைத்தெழு பொழில்மி குத்திடு",
        "தணிம லைக்குயர் ...... பெருமாளே."
    ],
    "full_text": "மலைமு லைச்சியர் கயல்வி ழிச்சியர்\nமதிமு கத்திய ...... ரழகான\nமயில்ந டைச்சியர் குயில்மொ ழிச்சியர்\nமனது ருக்கிக ...... ளணைமீதே\nகலைநெ கிழ்த்தியே உறவ ணைத்திடு\nகலவி யிற்றுவள் ...... பிணிதீராக்\nகசட னைக்குண அசட னைப்புகல்\nகதியில் வைப்பது ...... மொருநாளே\nகுலகி ரிக்குல முருவ விட்டமர்\nகுலவு சித்திர ...... முனைவேலா\nகுறவர் பெற்றிடு சிறுமி யைப்புணர்\nகுமர சற்குண ...... மயில்வீரா\nதலம திற்புக லமர ருற்றிடர்\nதனைய கற்றிய ...... அருளாளா\nதருநி ரைத்தெழு பொழில்மி குத்திடு\nதணிம லைக்குயர் ...... பெருமாளே."
}