{
    "song_number": 802,
    "title": "பாடல் 802",
    "category_or_place": "திலதைப்பதி",
    "raga": "....",
    "thala": "பொது / குறிப்பிடப்படவில்லை",
    "chandam_structure": "தனனத் தனன தந்த தனனத் தனன தந்த / தனனத் தனன தந்த ...... தனதான",
    "chandam": [
        "தனனத் தனன தந்த தனனத் தனன தந்த",
        "தனனத் தனன தந்த ...... தனதான"
    ],
    "lyrics": [
        "பனகப் படமி சைந்த முழையிற் றரள நின்று",
        "பாடர்பொற் பணிபு னைந்த ...... முலைமீதிற்",
        "பரிவற் றெரியு நெஞ்சில் முகிலிற் களிய கொண்டை",
        "படுபுட் பவன முன்றி ...... லியலாரும்",
        "அனமொத் திடுசி றந்த நடையிற் கிளியி னின்சொல்",
        "அழகிற் றனித ளர்ந்து ...... மதிமோக",
        "மளவிப் புளக கொங்கை குழையத் தழுவி யின்ப",
        "அலையிற் றிரிவ னென்று ...... மறிவோனே",
        "தனனத் தனன தந்த தனனத் தனன தந்த",
        "தனனத் தனன தந்த ...... தனதானா",
        "தகிடத் தகிட தந்த திமிதத் திமித வென்று",
        "தனிமத் தளமு ழங்க ...... வருவோனே",
        "செநெனற் கழனி பொங்கி திமிலக் கமல மண்டி",
        "செறிநற் கழைதி ரண்டு ...... வளமேவித்",
        "திருநற் சிகரி துங்க வரையைப் பெருவு கின்ற",
        "திலதைப் பதிய மர்ந்த ...... பெருமாளே."
    ],
    "full_text": "பனகப் படமி சைந்த முழையிற் றரள நின்று\nபாடர்பொற் பணிபு னைந்த ...... முலைமீதிற்\nபரிவற் றெரியு நெஞ்சில் முகிலிற் களிய கொண்டை\nபடுபுட் பவன முன்றி ...... லியலாரும்\nஅனமொத் திடுசி றந்த நடையிற் கிளியி னின்சொல்\nஅழகிற் றனித ளர்ந்து ...... மதிமோக\nமளவிப் புளக கொங்கை குழையத் தழுவி யின்ப\nஅலையிற் றிரிவ னென்று ...... மறிவோனே\nதனனத் தனன தந்த தனனத் தனன தந்த\nதனனத் தனன தந்த ...... தனதானா\nதகிடத் தகிட தந்த திமிதத் திமித வென்று\nதனிமத் தளமு ழங்க ...... வருவோனே\nசெநெனற் கழனி பொங்கி திமிலக் கமல மண்டி\nசெறிநற் கழைதி ரண்டு ...... வளமேவித்\nதிருநற் சிகரி துங்க வரையைப் பெருவு கின்ற\nதிலதைப் பதிய மர்ந்த ...... பெருமாளே."
}