{
    "song_number": 412,
    "title": "பாடல் 412",
    "category_or_place": "திருவருணை",
    "raga": "...",
    "thala": "பொது / குறிப்பிடப்படவில்லை",
    "chandam_structure": "தானா தத்தன தானா தத்தன / தந்தன தந்தன தான தந்தன / தானா தத்தன தானா தத்தன / தந்தன தந்தன தான தந்தன / தானா தத்தன தானா தத்தன / தந்தன தந்தன தான தந்தன ...... தந்ததான",
    "chandam": [
        "தானா தத்தன தானா தத்தன",
        "தந்தன தந்தன தான தந்தன",
        "தானா தத்தன தானா தத்தன",
        "தந்தன தந்தன தான தந்தன",
        "தானா தத்தன தானா தத்தன",
        "தந்தன தந்தன தான தந்தன ...... தந்ததான"
    ],
    "lyrics": [
        "காரா டக்குழ லாலா லக்கணை",
        "கண்கள் சுழன்றிட வேமு கங்களி",
        "னாலா பச்சிலை யாலே மெற்புசி",
        "மஞ்சள் கலந்தணி வாளி கொந்தள",
        "காதா டக்கலன் மேலா டக்குடி",
        "யின்ப ரசங்குட மார்ப ளிங்கொளி ...... கொங்கைமாதர்",
        "காசா சைச்செய லாலே சொக்கிடு",
        "விஞ்சையர் கொஞ்சிடு வாரி ளங்குயில்",
        "போலே நற்றெரு வூடா டித்துயல்",
        "தொங்கல் நெகிழ்ந்திடை யேது வண்டிட",
        "கால்தா விச்சதி யோடே சித்திர",
        "மென்ப நடம்புரி வாரு டன்செயல் ...... மிஞ்சலாகிச்",
        "சீரா டிச்சில நாள்போய் மெய்த்திரை",
        "வந்து கலந்துயி ரோட வங்கமொ",
        "டூடா டிப்பல நோயோ டுத்தடி",
        "கொண்டு குரங்கென வேந டந்துசொல்",
        "சீயோ டிக்கிடை பாயோ டுக்கிய",
        "டங்கி யழிந்துயி ரோடு ளைஞ்சொளி ...... யுங்கண்மாறிச்",
        "சேரா மற்பொறி கேளா மற்செவி",
        "துன்பமொ டின்பமு மேம றந்துபின்",
        "ஊரார் சுற்றமு மாதோர் மக்களு",
        "மண்டியு மண்டையு டேகு விந்திது",
        "சீசீ சிச்சிசி போகா நற்சனி",
        "யன்கட வென்றிட வேகி டந்துடல் ...... மங்குவேனோ",
        "மாரோன் முப்புர நிறா யுற்றிட",
        "அங்கி யுமிழ்ந்திடு வோரி பம்புலி",
        "தோல்சீ யத்தொடெ யேகா சர்ச்சடை",
        "கங்கை யிளம்பிறை யார ணிந்தவர்",
        "மாடே றிக்கட லாலா லத்தையு",
        "முண்டவ ரெந்தைசி வாநு பங்குறை ...... யென்றன்மாதா",
        "மாலோ னுக்கிளை யாள்மா பத்தினி",
        "யம்பிகை சங்கரி மோக சுந்தரி",
        "வேதா மக்கலை ரூபாள் முக்கணி",
        "ரம்பிய கொங்கையி னாள்ப யந்தருள்",
        "மாஞா னக்கும ராதோ கைப்பரி",
        "யின்பத வண்குரு வேயெ னஞ்சுரர் ...... தொண்டுபாடச்",
        "சூரார் மக்கிட மாமே ருக்கிட",
        "அங்கட லெண்கிரி யோடி பங்கொடு",
        "தீபே ழற்றிட பாதா ளத்துறை",
        "நஞ்சர வின்பண மாயி ரங்கெட",
        "சூழ்வா ளக்கிரி தூளா கிப்பொடி",
        "விண்கணி றைந்திட வேந டம்புரி ...... கின்றவேலா",
        "சோர்வே தத்தலை மேலா டிச்சுக",
        "பங்கய செங்கர மோட கம்பெற",
        "வாகா னக்குற மாதோ டற்புத",
        "மங்குல ணங்குட னேம கிழ்ந்துநல்",
        "தூணோ டிச்சுட ராகா சத்தைய",
        "ணைந்துவி ளங்கரு ணாச லந்திகழ் ...... தம்பிரானே."
    ],
    "full_text": "காரா டக்குழ லாலா லக்கணை\nகண்கள் சுழன்றிட வேமு கங்களி\nனாலா பச்சிலை யாலே மெற்புசி\nமஞ்சள் கலந்தணி வாளி கொந்தள\nகாதா டக்கலன் மேலா டக்குடி\nயின்ப ரசங்குட மார்ப ளிங்கொளி ...... கொங்கைமாதர்\nகாசா சைச்செய லாலே சொக்கிடு\nவிஞ்சையர் கொஞ்சிடு வாரி ளங்குயில்\nபோலே நற்றெரு வூடா டித்துயல்\nதொங்கல் நெகிழ்ந்திடை யேது வண்டிட\nகால்தா விச்சதி யோடே சித்திர\nமென்ப நடம்புரி வாரு டன்செயல் ...... மிஞ்சலாகிச்\nசீரா டிச்சில நாள்போய் மெய்த்திரை\nவந்து கலந்துயி ரோட வங்கமொ\nடூடா டிப்பல நோயோ டுத்தடி\nகொண்டு குரங்கென வேந டந்துசொல்\nசீயோ டிக்கிடை பாயோ டுக்கிய\nடங்கி யழிந்துயி ரோடு ளைஞ்சொளி ...... யுங்கண்மாறிச்\nசேரா மற்பொறி கேளா மற்செவி\nதுன்பமொ டின்பமு மேம றந்துபின்\nஊரார் சுற்றமு மாதோர் மக்களு\nமண்டியு மண்டையு டேகு விந்திது\nசீசீ சிச்சிசி போகா நற்சனி\nயன்கட வென்றிட வேகி டந்துடல் ...... மங்குவேனோ\nமாரோன் முப்புர நிறா யுற்றிட\nஅங்கி யுமிழ்ந்திடு வோரி பம்புலி\nதோல்சீ யத்தொடெ யேகா சர்ச்சடை\nகங்கை யிளம்பிறை யார ணிந்தவர்\nமாடே றிக்கட லாலா லத்தையு\nமுண்டவ ரெந்தைசி வாநு பங்குறை ...... யென்றன்மாதா\nமாலோ னுக்கிளை யாள்மா பத்தினி\nயம்பிகை சங்கரி மோக சுந்தரி\nவேதா மக்கலை ரூபாள் முக்கணி\nரம்பிய கொங்கையி னாள்ப யந்தருள்\nமாஞா னக்கும ராதோ கைப்பரி\nயின்பத வண்குரு வேயெ னஞ்சுரர் ...... தொண்டுபாடச்\nசூரார் மக்கிட மாமே ருக்கிட\nஅங்கட லெண்கிரி யோடி பங்கொடு\nதீபே ழற்றிட பாதா ளத்துறை\nநஞ்சர வின்பண மாயி ரங்கெட\nசூழ்வா ளக்கிரி தூளா கிப்பொடி\nவிண்கணி றைந்திட வேந டம்புரி ...... கின்றவேலா\nசோர்வே தத்தலை மேலா டிச்சுக\nபங்கய செங்கர மோட கம்பெற\nவாகா னக்குற மாதோ டற்புத\nமங்குல ணங்குட னேம கிழ்ந்துநல்\nதூணோ டிச்சுட ராகா சத்தைய\nணைந்துவி ளங்கரு ணாச லந்திகழ் ...... தம்பிரானே."
}