{
    "song_number": 455,
    "title": "பாடல் 455",
    "category_or_place": "சிதம்பரம்",
    "raga": "...",
    "thala": "பொது / குறிப்பிடப்படவில்லை",
    "chandam_structure": "தந்த தந்தன தந்த தந்தன / தந்த தந்தன தந்த தந்தன / தந்த தந்தன தந்த தந்தன ...... தனதான",
    "chandam": [
        "தந்த தந்தன தந்த தந்தன",
        "தந்த தந்தன தந்த தந்தன",
        "தந்த தந்தன தந்த தந்தன ...... தனதான"
    ],
    "lyrics": [
        "கொந்த ளம்புழு கெந்த வண்பனி",
        "ரம்ப சம்ப்ரம ணிந்த மந்தர",
        "கொங்கை வெண்கரி கொம்பி ணங்கிய ...... மடமாதர்",
        "கொந்த ணங்குழ லின்ப மஞ்சள",
        "ணிந்து சண்பக வஞ்சி ளங்கொடி",
        "கொஞ்சு பைங்கிளி யன்பெ னுங்குயில் ...... மயில்போலே",
        "வந்து பஞ்சணை யின்ப முங்கொடு",
        "கொங்கை யும்புய முந்த ழும்புற",
        "மஞ்சு வொண்கலை யுங்கு லைந்தவ ...... மயல்மேலாய்",
        "வஞ்சி னங்கள்தி ரண்டு கண்செவி",
        "யுஞ்சு கங்கள்தி ரும்பி முன்செய்த",
        "வஞ்சி னங்களு டன்கி டந்துட ...... லழிவேனோ",
        "தந்த னந்தன தந்த னந்தன",
        "திந்தி மிந்திமி திந்தி மிந்திமி",
        "சங்கு வெண்கல கொம்பு துந்துமி ...... பலபேரி",
        "சஞ்ச லஞ்சல கொஞ்சு கிண்கிணி",
        "தங்கு டுண்டுடு டுண்டு டன்பல",
        "சந்தி ரம்பறை பொங்கு வஞ்சகர் ...... களமீதே",
        "சிந்த வெண்கழு கொங்கு பொங்கெழு",
        "செம்பு ளங்கரு டன்ப ருந்துகள்",
        "செங்க ளந்திகை யெங்கு மண்டிட ...... விடும்வேலா",
        "திங்க ளிந்திர னும்ப ரந்தர",
        "ரும்பு கழ்ந்துரு கும்ப ரன்சபை",
        "செம்பொ னம்பல மங்கொ ளன்பர்கள் ...... பெருமாளே."
    ],
    "full_text": "கொந்த ளம்புழு கெந்த வண்பனி\nரம்ப சம்ப்ரம ணிந்த மந்தர\nகொங்கை வெண்கரி கொம்பி ணங்கிய ...... மடமாதர்\nகொந்த ணங்குழ லின்ப மஞ்சள\nணிந்து சண்பக வஞ்சி ளங்கொடி\nகொஞ்சு பைங்கிளி யன்பெ னுங்குயில் ...... மயில்போலே\nவந்து பஞ்சணை யின்ப முங்கொடு\nகொங்கை யும்புய முந்த ழும்புற\nமஞ்சு வொண்கலை யுங்கு லைந்தவ ...... மயல்மேலாய்\nவஞ்சி னங்கள்தி ரண்டு கண்செவி\nயுஞ்சு கங்கள்தி ரும்பி முன்செய்த\nவஞ்சி னங்களு டன்கி டந்துட ...... லழிவேனோ\nதந்த னந்தன தந்த னந்தன\nதிந்தி மிந்திமி திந்தி மிந்திமி\nசங்கு வெண்கல கொம்பு துந்துமி ...... பலபேரி\nசஞ்ச லஞ்சல கொஞ்சு கிண்கிணி\nதங்கு டுண்டுடு டுண்டு டன்பல\nசந்தி ரம்பறை பொங்கு வஞ்சகர் ...... களமீதே\nசிந்த வெண்கழு கொங்கு பொங்கெழு\nசெம்பு ளங்கரு டன்ப ருந்துகள்\nசெங்க ளந்திகை யெங்கு மண்டிட ...... விடும்வேலா\nதிங்க ளிந்திர னும்ப ரந்தர\nரும்பு கழ்ந்துரு கும்ப ரன்சபை\nசெம்பொ னம்பல மங்கொ ளன்பர்கள் ...... பெருமாளே."
}