{
    "song_number": 1297,
    "title": "பாடல் 1297",
    "category_or_place": "பொதுப்பாடல்கள்",
    "raga": "கானடா",
    "thala": "பொது / குறிப்பிடப்படவில்லை",
    "chandam_structure": "தத்தத் தனான ...... தனதான",
    "chandam": [
        "தத்தத் தனான ...... தனதான"
    ],
    "lyrics": [
        "பட்டு படாத ...... மதனாலும்",
        "பக்கத்து மாதர் ...... வசையாலும்",
        "சுட்டுச் சுடாத ...... நிலவாலும்",
        "துக்கத்தி லாழ்வ ...... தியல்போதான்",
        "தட்டுப் படாத ...... திறல்வீரா",
        "தர்க்கித்த சூரர் ...... குலகாலா",
        "மட்டுப் படாத ...... மயிலோனே",
        "மற்றொப்பி லாத ...... பெருமாளே."
    ],
    "full_text": "பட்டு படாத ...... மதனாலும்\nபக்கத்து மாதர் ...... வசையாலும்\nசுட்டுச் சுடாத ...... நிலவாலும்\nதுக்கத்தி லாழ்வ ...... தியல்போதான்\nதட்டுப் படாத ...... திறல்வீரா\nதர்க்கித்த சூரர் ...... குலகாலா\nமட்டுப் படாத ...... மயிலோனே\nமற்றொப்பி லாத ...... பெருமாளே."
}