{
    "song_number": 243,
    "title": "பாடல் 243",
    "category_or_place": "திருத்தணிகை",
    "raga": "அஸாவேரி",
    "thala": "மிஸ்ரசாபு",
    "chandam_structure": "",
    "chandam": [],
    "lyrics": [
        "தகதிமி-2, தகிட-1 1/2",
        "தனதன தான தனதன தான",
        "தனதன தான ...... தனதான",
        "இருமலு ரோக முயலகன் வாத",
        "மெரிகுண நாசி ...... விடமேநீ",
        "ரிழிவுவி டாத தலைவலி சோகை",
        "யெழுகள மாலை ...... யிவையோடே",
        "பெருவயி றீளை யெரிகுலை சூலை",
        "பெருவலி வேறு ...... முளநோய்கள்",
        "பிறவிகள் தோறு மெனைநலி யாத",
        "படியுன தாள்கள் ...... அருள்வாயே",
        "வருமொரு கோடி யசுரர்ப தாதி",
        "மடியஅ நேக ...... இசைபாடி",
        "வருமொரு கால வயிரவ ராட",
        "வடிசுடர் வேலை ...... விடுவோனே",
        "தருநிழல் மீதி லுறைமுகி லு஡ர்தி",
        "தருதரு மாதின் ...... மணவாளா",
        "சலமிடை பூவி னடுவினில் வீறு",
        "தணிமலை மேவு ...... பெருமாளே."
    ],
    "full_text": "தகதிமி-2, தகிட-1 1/2\nதனதன தான தனதன தான\nதனதன தான ...... தனதான\nஇருமலு ரோக முயலகன் வாத\nமெரிகுண நாசி ...... விடமேநீ\nரிழிவுவி டாத தலைவலி சோகை\nயெழுகள மாலை ...... யிவையோடே\nபெருவயி றீளை யெரிகுலை சூலை\nபெருவலி வேறு ...... முளநோய்கள்\nபிறவிகள் தோறு மெனைநலி யாத\nபடியுன தாள்கள் ...... அருள்வாயே\nவருமொரு கோடி யசுரர்ப தாதி\nமடியஅ நேக ...... இசைபாடி\nவருமொரு கால வயிரவ ராட\nவடிசுடர் வேலை ...... விடுவோனே\nதருநிழல் மீதி லுறைமுகி லு஡ர்தி\nதருதரு மாதின் ...... மணவாளா\nசலமிடை பூவி னடுவினில் வீறு\nதணிமலை மேவு ...... பெருமாளே."
}