{
    "song_number": 1237,
    "title": "பாடல் 1237",
    "category_or_place": "பொதுப்பாடல்கள்",
    "raga": "...",
    "thala": "பொது / குறிப்பிடப்படவில்லை",
    "chandam_structure": "தான தனன தத்த தான தனன தத்த / தான தனன தத்த ...... தனதான",
    "chandam": [
        "தான தனன தத்த தான தனன தத்த",
        "தான தனன தத்த ...... தனதான"
    ],
    "lyrics": [
        "கோக னகமு கிழ்த்த போக புளகி தத்த",
        "கோடு தலைகு லைத்த ...... முலையாலே",
        "கூட வரவ ழைக்கு மாடு குழைய டர்த்த",
        "நீடி யகுவ ளைக்கண் ...... மடமானார்",
        "ஆக முறவ ணைத்து காசை யபக ரித்து",
        "மீள விதழ்க டிப்ப ...... தறியாதே",
        "ஆசை யதுகொ ளுத்து மால மதுகு டித்த",
        "சேலில் பரித விப்ப ...... தினியேனோ",
        "மாக நதிம திப்ர தாப மவுலி யர்க்கு",
        "சாவி யதுவோ ரர்த்த ...... மொழிவோனே",
        "வாகு வலைய சித்ர ஆறி ருபுய வெற்பில்",
        "வாழ்வு பெருகு றத்தி ...... மணவாளா",
        "வேக வுரக ரத்ந நாக சயன சக்ர",
        "மேவி மரக தத்தின் ...... மருகோனே",
        "வீசு திரைய லைத்த வேலை சுவற வெற்றி",
        "வேலை யுருவ விட்ட ...... பெருமாளே."
    ],
    "full_text": "கோக னகமு கிழ்த்த போக புளகி தத்த\nகோடு தலைகு லைத்த ...... முலையாலே\nகூட வரவ ழைக்கு மாடு குழைய டர்த்த\nநீடி யகுவ ளைக்கண் ...... மடமானார்\nஆக முறவ ணைத்து காசை யபக ரித்து\nமீள விதழ்க டிப்ப ...... தறியாதே\nஆசை யதுகொ ளுத்து மால மதுகு டித்த\nசேலில் பரித விப்ப ...... தினியேனோ\nமாக நதிம திப்ர தாப மவுலி யர்க்கு\nசாவி யதுவோ ரர்த்த ...... மொழிவோனே\nவாகு வலைய சித்ர ஆறி ருபுய வெற்பில்\nவாழ்வு பெருகு றத்தி ...... மணவாளா\nவேக வுரக ரத்ந நாக சயன சக்ர\nமேவி மரக தத்தின் ...... மருகோனே\nவீசு திரைய லைத்த வேலை சுவற வெற்றி\nவேலை யுருவ விட்ட ...... பெருமாளே."
}