{
    "song_number": 181,
    "title": "பாடல் 181",
    "category_or_place": "பழநி",
    "raga": "....",
    "thala": "பொது / குறிப்பிடப்படவில்லை",
    "chandam_structure": "தனதனன தந்த தந்த தனதனன தந்த தந்த / தனதனன தந்த தந்த ...... தனதான",
    "chandam": [
        "தனதனன தந்த தந்த தனதனன தந்த தந்த",
        "தனதனன தந்த தந்த ...... தனதான"
    ],
    "lyrics": [
        "மருமலரி னன்து ரந்து விடவினைய ருந்த அந்தி",
        "மதியொடுபி றந்து முன்பெய் ...... வதையாலே",
        "வகைதனைம றந்தெ ழுந்து முலைதனைய ருந்தி யந்த",
        "மதலையென வந்து குன்றின் ...... வடிவாகி",
        "இருமயல்கொ டுந்து வண்டு பொதுவையர கம்பு குந்து",
        "இரவுபகல் கொண்டொ டுங்கி ...... யசடாகும்",
        "இருவினைபொ திந்த இந்த ஜனனமர ணந்து றந்து",
        "னிணையடிவ ணங்க என்று ...... பெறுவேனோ",
        "திருவொடுபெ யர்ந்தி ருண்ட வனமிசைந டந்தி லங்கை",
        "திகழெரியி டுங்கு ரங்கை ...... நெகிழாத",
        "திடமுளமு குந்தர் கஞ்சன் வரவிடுமெல் வஞ்ச கங்கள்",
        "செறிவுடன் றிந்து வென்ற ...... பொறியாளர்",
        "பரிவொடும கிழ்ந்தி றைஞ்சு மருதிடைத வழ்ந்து நின்ற",
        "பரமபத நண்ப ரன்பின் ...... மருகோனே",
        "பதுமமிசை வண்ட லம்பு சுனைபலவி ளங்கு துங்க",
        "பழநிமலை வந்த மர்ந்த ...... பெருமாளே."
    ],
    "full_text": "மருமலரி னன்து ரந்து விடவினைய ருந்த அந்தி\nமதியொடுபி றந்து முன்பெய் ...... வதையாலே\nவகைதனைம றந்தெ ழுந்து முலைதனைய ருந்தி யந்த\nமதலையென வந்து குன்றின் ...... வடிவாகி\nஇருமயல்கொ டுந்து வண்டு பொதுவையர கம்பு குந்து\nஇரவுபகல் கொண்டொ டுங்கி ...... யசடாகும்\nஇருவினைபொ திந்த இந்த ஜனனமர ணந்து றந்து\nனிணையடிவ ணங்க என்று ...... பெறுவேனோ\nதிருவொடுபெ யர்ந்தி ருண்ட வனமிசைந டந்தி லங்கை\nதிகழெரியி டுங்கு ரங்கை ...... நெகிழாத\nதிடமுளமு குந்தர் கஞ்சன் வரவிடுமெல் வஞ்ச கங்கள்\nசெறிவுடன் றிந்து வென்ற ...... பொறியாளர்\nபரிவொடும கிழ்ந்தி றைஞ்சு மருதிடைத வழ்ந்து நின்ற\nபரமபத நண்ப ரன்பின் ...... மருகோனே\nபதுமமிசை வண்ட லம்பு சுனைபலவி ளங்கு துங்க\nபழநிமலை வந்த மர்ந்த ...... பெருமாளே."
}