{
    "song_number": 476,
    "title": "பாடல் 476",
    "category_or_place": "சிதம்பரம்",
    "raga": "...",
    "thala": "பொது / குறிப்பிடப்படவில்லை",
    "chandam_structure": "",
    "chandam": [],
    "lyrics": [
        "தத்த தன்ன தய்ய தத்த தன்ன தய்ய",
        "தத்த தன்ன தய்ய ...... தனதான",
        "அத்த னன்னை யில்லம் வைத்த சொன்னம் வெள்ளி",
        "அத்தை நண்ணு செல்வ ...... ருடனாகி",
        "அத்து பண்ணு கல்வி சுற்ற மென்னு மல்ல",
        "லற்று நின்னை வல்ல ...... படிபாடி",
        "முத்த னென்ன வல்லை யத்த னென்ன வள்ளி",
        "முத்த னென்ன வுள்ள ...... முணராதே",
        "முட்ட வெண்மை யுள்ள பட்ட னெண்மை கொள்ளு",
        "முட்ட னிங்ங னைவ ...... தொழியாதோ",
        "தித்தி மன்னு தில்லை நிர்த்தர் கண்ணி னுள்ளு",
        "தித்து மன்னு பிள்ளை ...... முருகோனே",
        "சித்தி மன்னு செய்ய சத்தி துன்னு கைய",
        "சித்ர வண்ண வல்லி ...... யலர்சூடும்",
        "பத்த ருண்மை சொல்லு ளுற்ற செம்மல் வெள்ளி",
        "பத்தர் கன்னி புல்லு ...... மணிமார்பா",
        "பச்சை வன்னி யல்லி செச்சை சென்னி யுள்ள",
        "பச்சை மஞ்ஞை வல்ல ...... பெருமாளே."
    ],
    "full_text": "தத்த தன்ன தய்ய தத்த தன்ன தய்ய\nதத்த தன்ன தய்ய ...... தனதான\nஅத்த னன்னை யில்லம் வைத்த சொன்னம் வெள்ளி\nஅத்தை நண்ணு செல்வ ...... ருடனாகி\nஅத்து பண்ணு கல்வி சுற்ற மென்னு மல்ல\nலற்று நின்னை வல்ல ...... படிபாடி\nமுத்த னென்ன வல்லை யத்த னென்ன வள்ளி\nமுத்த னென்ன வுள்ள ...... முணராதே\nமுட்ட வெண்மை யுள்ள பட்ட னெண்மை கொள்ளு\nமுட்ட னிங்ங னைவ ...... தொழியாதோ\nதித்தி மன்னு தில்லை நிர்த்தர் கண்ணி னுள்ளு\nதித்து மன்னு பிள்ளை ...... முருகோனே\nசித்தி மன்னு செய்ய சத்தி துன்னு கைய\nசித்ர வண்ண வல்லி ...... யலர்சூடும்\nபத்த ருண்மை சொல்லு ளுற்ற செம்மல் வெள்ளி\nபத்தர் கன்னி புல்லு ...... மணிமார்பா\nபச்சை வன்னி யல்லி செச்சை சென்னி யுள்ள\nபச்சை மஞ்ஞை வல்ல ...... பெருமாளே."
}